pytorchcvtcolor/__init__.py
pytorchcvtcolor/cvt_color.py
pytorchcvtcolor/gray.py
pytorchcvtcolor/hsv.py
pytorchcvtcolor/image.py
pytorchcvtcolor/rgb.py
pytorchcvtcolor/ycbcr.py
pytorchcvtcolor-0.1.dev1.dist-info/LICENSE
pytorchcvtcolor-0.1.dev1.dist-info/METADATA
pytorchcvtcolor-0.1.dev1.dist-info/WHEEL
pytorchcvtcolor-0.1.dev1.dist-info/top_level.txt
pytorchcvtcolor-0.1.dev1.dist-info/RECORD
