Metadata-Version: 2.1
Name: pytorchcvtcolor
Version: 0.1.dev1
Summary: Python library for PyTorch Color Convertor
Home-page: https://github.com/shashimalcse/pytorchisland
Author: Shashimal Senarath
Author-email: shashimalsenarathz97@gmail.com
License: MIT
Platform: UNKNOWN
Classifier: License :: OSI Approved :: MIT License
Classifier: Programming Language :: Python
Classifier: Programming Language :: Python :: 3
Classifier: Programming Language :: Python :: Implementation :: CPython
Classifier: Programming Language :: Python :: Implementation :: PyPy
Requires-Python: >=3.0.0
Provides-Extra: test
License-File: LICENSE
